setup.py
akudeevia_distribution_pkg/Binomialdistribution.py
akudeevia_distribution_pkg/Gaussiandistribution.py
akudeevia_distribution_pkg/Generaldistribution.py
akudeevia_distribution_pkg/__init__.py
akudeevia_distribution_pkg.egg-info/PKG-INFO
akudeevia_distribution_pkg.egg-info/SOURCES.txt
akudeevia_distribution_pkg.egg-info/dependency_links.txt
akudeevia_distribution_pkg.egg-info/not-zip-safe
akudeevia_distribution_pkg.egg-info/top_level.txt