Metadata-Version: 1.0
Name: akudeevia-distribution-pkg
Version: 0.1
Summary: Gaussian & Binomial distributions
Home-page: UNKNOWN
Author: Akshay Kulkarni
Author-email: UNKNOWN
License: UNKNOWN
Platform: UNKNOWN
